passive_honeypot_OTTODANP/__init__.py
passive_honeypot_OTTODANP/config.py
passive_honeypot_OTTODANP/database.py
passive_honeypot_OTTODANP/favicon.ico
passive_honeypot_OTTODANP/honeypot.py
passive_honeypot_OTTODANP/templates/home.html
passive_honeypot_OTTODANP/templates/navbar.html
passive_honeypot_OTTODANP/templates/view_hosts.html
passive_honeypot_OTTODANP/templates/view_requests.html
passive_honeypot_ottodanp-0.1.0.dist-info/LICENSE
passive_honeypot_ottodanp-0.1.0.dist-info/METADATA
passive_honeypot_ottodanp-0.1.0.dist-info/WHEEL
passive_honeypot_ottodanp-0.1.0.dist-info/RECORD
